odoo/addons/coupon_commercial_partner_applicability/README.rst
odoo/addons/coupon_commercial_partner_applicability/__init__.py
odoo/addons/coupon_commercial_partner_applicability/__manifest__.py
odoo/addons/coupon_commercial_partner_applicability/i18n/coupon_commercial_partner_applicability.pot
odoo/addons/coupon_commercial_partner_applicability/models/__init__.py
odoo/addons/coupon_commercial_partner_applicability/models/coupon_coupon.py
odoo/addons/coupon_commercial_partner_applicability/readme/CONTRIBUTORS.rst
odoo/addons/coupon_commercial_partner_applicability/readme/DESCRIPTION.rst
odoo/addons/coupon_commercial_partner_applicability/static/description/icon.png
odoo/addons/coupon_commercial_partner_applicability/static/description/index.html
odoo/addons/coupon_commercial_partner_applicability/tests/__init__.py
odoo/addons/coupon_commercial_partner_applicability/tests/test_sale_coupon_apply_commercial_partner.py
odoo_addon_coupon_commercial_partner_applicability-15.0.1.0.0.5.dist-info/METADATA
odoo_addon_coupon_commercial_partner_applicability-15.0.1.0.0.5.dist-info/WHEEL
odoo_addon_coupon_commercial_partner_applicability-15.0.1.0.0.5.dist-info/top_level.txt
odoo_addon_coupon_commercial_partner_applicability-15.0.1.0.0.5.dist-info/RECORD
